MANIFEST.in
setup.py
angel_web/__init__.py
angel_web/app.py
angel_web/job.py
angel_web/log.py
angel_web/resource.py
angel_web/task.py
angel_web.egg-info/PKG-INFO
angel_web.egg-info/SOURCES.txt
angel_web.egg-info/dependency_links.txt
angel_web.egg-info/entry_points.txt
angel_web.egg-info/not-zip-safe
angel_web.egg-info/requires.txt
angel_web.egg-info/top_level.txt
angel_web/core/__init__.py
angel_web/core/config_util.py
angel_web/core/ftp_client.py
angel_web/core/json_util.py
angel_web/core/message.py
angel_web/html/alive_tasks.html
angel_web/html/alive_workers.html
angel_web/html/all_tasks.html
angel_web/html/index.html
angel_web/html/job_depends.html
angel_web/html/job_groups.html
angel_web/html/jobs.html
angel_web/html/log.html
angel_web/html/pending_tasks.html
angel_web/html/task_groups.html
angel_web/html/template.html
angel_web/html/upload.html
angel_web/html/worker_groups.html
angel_web/html/workers.html
angel_web/static/favicon.ico
angel_web/static/menu.json
angel_web/static/success.json
angel_web/static/B-JUI/js/bjui-all.js
angel_web/static/B-JUI/js/bjui-all.min.js
angel_web/static/B-JUI/js/bjui-all.min.js.map
angel_web/static/B-JUI/js/jquery-1.11.3.min.js
angel_web/static/B-JUI/js/jquery.cookie.js
angel_web/static/B-JUI/js/socket.io.min.js
angel_web/static/B-JUI/other/html5shiv.min.js
angel_web/static/B-JUI/other/ie10-viewport-bug-workaround.js
angel_web/static/B-JUI/other/jquery.iframe-transport.js
angel_web/static/B-JUI/other/respond.min.js
angel_web/static/B-JUI/plugins/bootstrap.js
angel_web/static/B-JUI/plugins/bootstrap.min.js
angel_web/static/B-JUI/plugins/bootstrapSelect/bootstrap-select.css
angel_web/static/B-JUI/plugins/bootstrapSelect/bootstrap-select.css.map
angel_web/static/B-JUI/plugins/bootstrapSelect/bootstrap-select.js
angel_web/static/B-JUI/plugins/bootstrapSelect/bootstrap-select.js.map
angel_web/static/B-JUI/plugins/bootstrapSelect/bootstrap-select.min.js
angel_web/static/B-JUI/plugins/bootstrapSelect/defaults-zh_CN.js
angel_web/static/B-JUI/plugins/bootstrapSelect/defaults-zh_CN.min.js
angel_web/static/B-JUI/plugins/colorpicker/css/bootstrap-colorpicker.css
angel_web/static/B-JUI/plugins/colorpicker/css/bootstrap-colorpicker.min.css
