Metadata-Version: 1.1
Name: angel-web
Version: 1.0.26
Summary: The admin web dashboard of a distribute job scheduler named 'angel'
Home-page: https://pypi.python.org/pypi/angel_web
Author: Lafite93
Author-email: 2273337844@qq.com
License: Apache
Keywords: angel admin web dashboard
Platform: Linux
Platform: Unix
Classifier: Programming Language :: Python :: 3
Classifier: Programming Language :: Python :: 3.5
